playerdo/__init__.py
playerdo/cli.py
playerdo/install.py
playerdo/main.py
playerdo/utils.py
playerdo/backends/__init__.py
playerdo/backends/banshee.py
playerdo/backends/base.py
playerdo/backends/cmus.py
playerdo/backends/moc.py
playerdo/backends/mpd.py
playerdo/backends/mpris2.py
playerdo/backends/pianobar.py
playerdo/backends/quodlibet.py
playerdo/backends/rhythmbox.py
playerdo/backends/shellfm.py
playerdo/backends/socket.py
playerdo-2.2.dist-info/LICENSE.txt
playerdo-2.2.dist-info/METADATA
playerdo-2.2.dist-info/WHEEL
playerdo-2.2.dist-info/entry_points.txt
playerdo-2.2.dist-info/top_level.txt
playerdo-2.2.dist-info/RECORD
