Metadata-Version: 2.1
Name: playerdo
Version: 2.2
Summary: Control various media players from a single command line interface.
Author-email: Luke Plant <luke@lukeplant.me.uk>
License: BSD
Project-URL: Homepage, http://bitbucket.org/spookylukey/playerdo
Keywords: music media MPRIS player command interface wrapper
Classifier: Topic :: Multimedia :: Sound/Audio :: Players
Classifier: License :: OSI Approved :: BSD License
Classifier: Development Status :: 5 - Production/Stable
Classifier: Intended Audience :: End Users/Desktop
Classifier: Operating System :: POSIX :: Linux
Classifier: Programming Language :: Python :: 3
Classifier: Programming Language :: Python :: 3.8
Classifier: Programming Language :: Python :: 3.9
Classifier: Programming Language :: Python :: 3.10
Classifier: Programming Language :: Python :: 3.11
Classifier: Programming Language :: Python :: 3.12
Requires-Python: >=3.8
License-File: LICENSE.txt
Requires-Dist: dbus-python >=1.3.2
